characterpy/__init__.py
characterpy/charPy.py
characterpy-0.1.0.dist-info/METADATA
characterpy-0.1.0.dist-info/WHEEL
characterpy-0.1.0.dist-info/top_level.txt
characterpy-0.1.0.dist-info/RECORD
