Metadata-Version: 2.4
Name: characterpy
Version: 0.1.0
Summary: Python in house 5E character builder and display
Author: AlexLovesEggos
License: MIT
Requires-Python: >=3.9
